listdiffcopy/LoggerObj.py
listdiffcopy/StorageAction2.py
listdiffcopy/StorageBase.py
listdiffcopy/StorageGitHub.py
listdiffcopy/StorageLocal.py
listdiffcopy/StorageMySQL.py
listdiffcopy/StoragePCloud.py
listdiffcopy/StorageSFTP.py
listdiffcopy/StorageWeb.py
listdiffcopy/StorageWebMedium.py
listdiffcopy/__init__.py
listdiffcopy/jpg_quality_pil_magick.py
listdiffcopy/logging_config.py
listdiffcopy/settings.py
listdiffcopy/storage_actions.py
listdiffcopy/utils.py
listdiffcopy-0.55598.dist-info/METADATA
listdiffcopy-0.55598.dist-info/WHEEL
listdiffcopy-0.55598.dist-info/licenses/LICENSE
listdiffcopy-0.55598.dist-info/RECORD
